README.md
setup.cfg
setup.py
slt/__init__.py
slt.egg-info/PKG-INFO
slt.egg-info/SOURCES.txt
slt.egg-info/dependency_links.txt
slt.egg-info/entry_points.txt
slt.egg-info/requires.txt
slt.egg-info/top_level.txt
slt/scraper/__init__.py
slt/scraper/captcha.py