Metadata-Version: 1.2
Name: slt
Version: 0.10.3
Summary: Unofficial usage checker for SLT Internet
Home-page: https://github.com/r3b311i0n/slt-usage
Author: Amal Karunarathna
Author-email: nasashinega@gmail.com
License: UNKNOWN
Download-URL: https://github.com/r3b311i0n/slt-usage/archive/0.9.0.tar.gz
Keywords: lk,sri lanka,internet,isp,terminal,internet usage,slt,selenium
Platform: UNKNOWN
Classifier: Development Status :: 4 - Beta
Classifier: Intended Audience :: End Users/Desktop
Classifier: Intended Audience :: Telecommunications Industry
Classifier: License :: OSI Approved :: MIT License
Classifier: Programming Language :: Python :: 3.6
Requires-Python: >=3.6
